shpkpr/__init__.py
shpkpr/exceptions.py
shpkpr/template.py
shpkpr/template_filters.py
shpkpr/vault.py
shpkpr/cli/__init__.py
shpkpr/cli/arguments.py
shpkpr/cli/decorators.py
shpkpr/cli/entrypoint.py
shpkpr/cli/formatter.py
shpkpr/cli/logger.py
shpkpr/cli/options.py
shpkpr/commands/__init__.py
shpkpr/commands/cmd_apps.py
shpkpr/commands/cmd_cron.py
shpkpr/deployment/__init__.py
shpkpr/deployment/standard.py
shpkpr/deployment/bluegreen/__init__.py
shpkpr/deployment/bluegreen/deployment.py
shpkpr/deployment/bluegreen/prepare.py
shpkpr/deployment/bluegreen/stats.py
shpkpr/deployment/bluegreen/validate.py
shpkpr/deployment/bluegreen/wait.py
shpkpr/marathon/__init__.py
shpkpr/marathon/client.py
shpkpr/marathon/deployment.py
shpkpr/marathon_lb/__init__.py
shpkpr/marathon_lb/client.py
shpkpr/marathon_lb/resolver.py
shpkpr/marathon_lb/stats.py
shpkpr/resources/templates/chronos/default/job.json.tmpl
shpkpr/resources/templates/marathon/default/bluegreen.json.tmpl
shpkpr/resources/templates/marathon/default/standard.json.tmpl
shpkpr-4.1.2.dist-info/LICENSE.txt
shpkpr-4.1.2.dist-info/METADATA
shpkpr-4.1.2.dist-info/WHEEL
shpkpr-4.1.2.dist-info/entry_points.txt
shpkpr-4.1.2.dist-info/top_level.txt
shpkpr-4.1.2.dist-info/RECORD
