Metadata-Version: 2.1
Name: shpkpr
Version: 4.1.2
Summary: shpkpr is a command-line tool designed to manage applications running on Marathon
Home-page: https://github.com/shopkeep/shpkpr
Author: ShopKeep.com Inc.
Author-email: developers@shopkeep.com
License: MIT
Keywords: shpkpr mesos marathon chronos
Platform: UNKNOWN
Classifier: Development Status :: 5 - Production/Stable
Classifier: Intended Audience :: Developers
Classifier: License :: OSI Approved :: MIT License
Classifier: Natural Language :: English
Classifier: Programming Language :: Python
Classifier: Programming Language :: Python :: 2
Classifier: Programming Language :: Python :: 2.7
Classifier: Programming Language :: Python :: 3
Classifier: Programming Language :: Python :: 3.4
Classifier: Programming Language :: Python :: 3.5
Classifier: Programming Language :: Python :: 3.6
Classifier: Programming Language :: Python :: Implementation :: PyPy
Requires-Dist: PyYAML (>=3.10.0)
Requires-Dist: cached-property (<2,>=1.3.0)
Requires-Dist: chronos-python (>=1.1.0)
Requires-Dist: click (<7,>=6.0)
Requires-Dist: docker (>=3.0.0)
Requires-Dist: hvac (>=0.2.17)
Requires-Dist: jinja2 (<3,>=2.6)
Requires-Dist: jsonschema (<3,>=2.6)
Requires-Dist: python-slugify (>=1.2.4)
Requires-Dist: six (>=1.11.0)
Requires-Dist: requests (>=2.4.2)
